design.sv
// Code your design here
module alu #(parameter V=8)
  (input init,
                            input [3:0]opco,
                            input [V-1:0]a,
                            input [V-1:0]b,
                            output reg [15:0]deco,
   
                            output reg [V-1:0]add,
                            output reg [V-1:0]sub,
                            output reg [15:0]mul,
                            output reg [V-1:0]div,
   
                            output reg [V-1:0]andd,
                            output reg [V-1:0] orr,
                            output reg [V-1:0] nott,
                            output reg [V-1:0]nandd,
                            output reg [V-1:0]norr,
                            output reg [V-1:0]xorr,
   
                            output reg [V-1:0]refresh,
   
                            output reg [V-1:0]comp,
   
                            output reg [V-1:0] sh_result,
                            output reg [V-1:0]ro_result,
                            output reg [V-1:0]s,
   
                            output reg [V-1:0] ccin,
   
                            output reg [3:0] cc,
                            output reg xs3tens_bit,
                            output reg xs5tens_bit,
                            output reg bcdtens_bit,
                            output reg [4:0]rfetch,
                            output reg [15:0] out,
               output reg carryflag,logflag,zeroflag,shiftflag,doneflag);
  reg [8:0] temp_sum;
   wire s1,s2;
  reg [V-1:0] shl,shr,shll,shrr,rol,ror,roll,rorr;
  reg [V-1:0] g,xs3,xs5,bcd;
   reg arth_flag, logi_flag, comp_flag, shft_flag, code_flag;
 always@(*)
    begin
      if (!init) begin   
        deco       = 16'b0;
        add        = 8'b0;
        sub        = 8'b0;
        mul        = 16'b0;
        div        = 16'b0;
        andd       = 8'b0;
        orr        = 8'b0;
        nott       = 8'b0;
        nandd      = 8'b0;
        norr       = 8'b0;
        xorr       = 8'b0;
        refresh    = 8'b0;
        carryflag=1'b0;
        logflag=1'b0;
    end
      else begin
     case(opco)
       4'b0000: begin
         deco=16'b0000000000000000;
       end
        4'b0001:begin
          deco=16'b0000000000000001;
          temp_sum= a + b;          
          add = temp_sum[7:0]; 
          carryflag = temp_sum[8];  
        end
        4'b0010:begin
          deco=16'b0000000000000010;
          sub=a-b;
          carryflag=(a<b)?1'b1:1'b0;
        end
          4'b0011:begin
            deco=16'b0000000000000100;
            mul=a*b;
            carryflag=(mul>16'hffff)?1'b1:1'b0;
          end
            4'b0100:begin
              deco=16'b0000000000001000;
              if(b==0)begin
              div=8'b0;
              carryflag=1'b1;
              end
             else begin
              div=a/b;
              carryflag=1'b0; 
              end
            end
        4'b0101:begin
          deco=16'b0000000000010000;
          andd=a&b;
          logflag=1'b1;
        end
        4'b0110:begin
        deco=16'b0000000000100000;
        orr=a|b;
        logflag=1'b1;
        end
        4'b0111:begin
          deco=16'b0000000001000000;
          nott=~a;
          logflag=1'b1;
        end
        4'b1000:begin
          deco=16'b0000000010000000;
          nandd=~(a & b);
          logflag=1'b1;
        end
        4'b1001:begin
          deco=16'b0000000100000000;
          norr=~(a | b);
          logflag=1'b1;
        end
        4'b1010:begin
          deco=16'b0000001000000000;
          xorr=a^b;
          logflag=1'b1;
        end
       4'b1011: begin
        deco=16'b0000010000000000;
        carryflag=1'b0;
        logflag=1'b0;
         refresh=8'b00000000;
      end
     default:begin
        deco=16'b0000000000000000;
         carryflag=1'b0;
          logflag=1'b0;
       refresh=8'b00000000;
      end
      endcase
      end
      end  
assign s1=a>b;
assign s2=a<b;
 always @(*) begin
   if (!init) begin
     deco=16'b0;
     comp=8'b00000000;
     carryflag=1'b0;
     zeroflag=1'b0;
   end
   else begin
     if(opco == 4'b1100)begin
    case (opco)
        4'b1100: begin
        deco = 16'b0000100000000000;
          if ({s1,s2}==2'b00) begin
                comp = 8'b0;
                carryflag  = 1'b0;
                zeroflag   = 1'b1;
            end 
          else if (s1==1) begin
                comp  = 8'b10000000; 
                carryflag  = 1'b0;
                zeroflag   = 1'b0;
            end 
          else if(s2==1)begin
                comp   = 8'b00000001; 
                carryflag  = 1'b1;
                zeroflag   = 1'b0;
            end
        end

        default: begin
            deco      = 16'b0000000000000000;
            carryflag = 1'b0;
            zeroflag=1'b0;
        end
    endcase
   end
   end
 end
  always @(*) begin
    if(!init) begin
    shl        = 8'b0;
    shr        = 8'b0;
    shll       = 8'b0;
    shrr       = 8'b0;
    rol        = 8'b0;
    ror        = 8'b0;
    roll       = 8'b0;
    rorr       = 8'b0;
    sh_result  = 8'b0;
    ro_result  = 8'b0;
    s          = 8'b0;
    shiftflag  = 1'b0;
    end
    else begin
      case(opco) 
        4'b1101: begin
      deco = 16'b0001_0000_0000_0000;
      if (!b[0]) begin
        shl = a << 1;       
        shiftflag = 1'b1;
      end
      if (!b[1]) begin
        shr = a >> 1;        
        shiftflag = 1'b1;
      end
      if (!b[2]) begin
        shll = a << b[3:0];    
        shiftflag = 1'b1;
      end
      if (!b[3]) begin
        shrr = a >> b[3:0];    
        shiftflag = 1'b1;
      end
      sh_result = shl | shr | shll | shrr;

   if (!b[4]) begin
     rol = {a[6:0], a[7]}; 
   //  rol = (A << 1) | (A >> (N - 1))
     shiftflag = 1'b1;
      end
   if (!b[5]) begin
     ror = {a[0], a[7:1]};
     shiftflag = 1'b1;
      end
   if (!b[6]) begin
     roll = (a << (b[7:4]&3'b111)) | (a >> (8 - (b[7:4]&3'b111)));                
      shiftflag = 1'b1;
      end
      if (!b[7]) begin
        rorr = (a >> (b[7:4]&3'b111)) | (a << (8 - (b[7:4]&3'b111)));        
        shiftflag = 1'b1;
      end
    ro_result = rol | ror | roll | rorr;
    s = sh_result | ro_result;
    end
      endcase
  end
  end
  always@(*) begin
     if(!init) begin
       ccin=8'b0;
     end
  else begin
     if(shiftflag)
            ccin=s;
          else
            ccin=b;
        end
     end
 always @(*) begin
        if (!init) begin
            cc        = 4'b0000;
            xs3tens_bit  = 1'b0;
            xs5tens_bit=1'b0;
            bcdtens_bit=1'b0;
            doneflag  = 1'b0;
            deco      = 16'b0;
            g         = 4'b0;
            xs3       = 4'b0;
            xs5       = 4'b0;
            bcd       = 4'b0;
        end
        else begin
          case (opco)
                4'b1110: begin
                    deco = 16'b0010_0000_0000_0000;  
                    if (!ccin[0]) begin
                        g[3] = ccin[7];
                        g[2] = ccin[7] ^ ccin[6];
                        g[1] = ccin[6] ^ ccin[5];
                        g[0] = ccin[5] ^ ccin[4];
                        doneflag = 1'b1;
                    end
                 if (!ccin[1]) begin
                   if(ccin[7:4] <10)begin
                     xs3 = ccin[7:4] + 4'b0011;  
                       xs3tens_bit=0;
                     doneflag=1;
                   end
                   else begin
                    // xs3ones_bits=cccin[7:4]%10;
                     xs3=((ccin[7:4]%10)+4'b0011);
                     xs3tens_bit=1;
                     doneflag = 1'b1;
                   end
                    end
                if (!ccin[2]) begin
                  if(ccin[7:4] <10)begin
                    xs5 = ccin[7:4] + 4'b0101;
                        xs5tens_bit=0;
                        doneflag = 1'b1;
                  end
                  else begin
                     //xs5ones_bits=ccin[7:4]%10;
                    xs5=((ccin[7:4]%10)+4'b0101);
                     xs5tens_bit=1;
                     doneflag = 1'b1;
                  end
                    end
                 if (!ccin[3]) begin
                   if (ccin[7:4] < 4'b1001) begin
                            bcd = ccin[7:4];
                            bcdtens_bit = 1'b0;
                        end 
                        else begin
                            bcd = ccin[7:4] - 4'b1010;
                            bcdtens_bit = 1'b1;
                        end
                        doneflag = 1'b1;
                    end
                     cc = g | xs3 | xs5 | bcd;
                end
                default: begin
                   xs3tens_bit=1'b0;
                  xs5tens_bit=1'b0;
                    bcdtens_bit  = 1'b0;
                    doneflag  = 1'b0;
                end
            endcase
        end
    end
always@(*) begin
    if(!init) begin
      deco=16'b0;
    arth_flag=1'b0;
    logi_flag=1'b0;
    comp_flag=1'b0;
    shft_flag=1'b0;
    code_flag=1'b0;
      rfetch=5'b0;
    end
    else begin
    case(opco)
        4'b1111: begin
       deco = 16'b0100_0000_0000_0000; 

   arth_flag=(add != 0 || sub != 0 || mul != 0 || div != 0) ? 1'b1 : 1'b0;
   logi_flag=(andd != 0 || orr != 0 || nott != 0 || nandd != 0 || norr != 0 || xorr != 0) ? 1'b1 : 1'b0;
   comp_flag=(comp != 0)?1'b1:1'b0;
   shft_flag=(s != 0)?1'b1:1'b0;
   code_flag=(cc != 0)?1'b1:1'b0;
   rfetch = {arth_flag, logi_flag, comp_flag, shft_flag, code_flag};
end
      default: begin
      rfetch=5'b00000;
      end
    endcase
  end
  end
always@(*)
    begin
      if(!init) begin
        out=16'b0;
      end
      else begin
      case(opco)
        4'b0000: begin
          out=16'b0000000000000000;
        end
        4'b0001: begin
          out=add;
        end
        4'b0010: begin
          out=sub;
        end
        4'b0011: begin
          out=mul;
        end
        4'b0100: begin
          out=div;
        end
        4'b0101: begin
          out=andd;
        end
        4'b0110: begin
          out=orr;
        end
        4'b0111: begin
          out=nott;
        end
          4'b1000: begin
            out=nandd;
          end
        4'b1001: begin
          out=norr;
        end
        4'b1010: begin
          out=xorr;
        end
        4'b1011: begin
          out=refresh;
        end
        4'b1100: begin
          out=comp;
        end
        4'b1101: begin
          out=s;
        end
       
        4'b1110: begin
          out=cc;
        end
        4'b1111: begin
          out=rfetch;
        end
        default: begin
          out=16'b0000000000000000;
        end
      endcase
    end
    end
endmodule

testbench.sv
// Code your testbench here
// or browse Examples
module tb();
  reg init;
  reg [3:0]opco;
  reg [7:0]a;
  reg [7:0]b;
  wire [15:0]deco;
  wire [7:0]add;
  wire [7:0]sub;
  wire [15:0]mul;
  wire [7:0]div;
  wire [7:0]andd;
  wire [7:0]orr;
  wire [7:0]nott;
  wire [7:0]nandd;
  wire [7:0]norr;
  wire [7:0]xorr;
  wire [7:0] refresh;
  wire [7:0]comp; 
  wire [7:0] sh_result;
  wire [7:0] ro_result;
  wire [7:0] s;
    wire [7:0]ccin;
  wire [3:0]cc;
  wire [4:0] rfetch;
  wire [15:0] out;
wire carryflag,logflag,zeroflag,shiftflag,doneflag;
  wire [8:0] temp_sum;
    wire [7:0] shl,shr,shll,shrr,rol,ror,roll,rorr;
   wire [7:0] g,xs3,xs5,bcd;
  wire xs3tens_bit,xs5tens_bit,bcdtens_bit;
  wire arth_flag, logi_flag, comp_flag, shft_flag, code_flag;
  alu uut(init,opco,a,b,deco,add,sub,mul,div,andd,orr,nott,nandd,norr,xorr,refresh,comp,sh_result,ro_result,s,ccin,cc,xs3tens_bit,xs5tens_bit,bcdtens_bit,rfetch,out,carryflag,logflag,zeroflag,shiftflag,doneflag);
  initial begin
       $dumpfile("waveform.vcd");
    $dumpvars(0, tb);
    
     init=1'b0;
    #5
  a = 8'b11100010;  
  b = 8'b10001100;
    init=1'b1;
  // a=8'b10001000;
 //  b=8'b10001000;
 //  a=8'b01000110;
 //   b=8'b11100000;
 
    #5;
    opco=4'b0000;
    #5;
    opco=4'b0001;
    #5;
    opco=4'b0010;
    #5;
    opco=4'b0011;
    #5;
    opco=4'b0100;
     #5;
    opco=4'b0101;
    #5;
    opco=4'b0110;
    #5;
    opco=4'b0111;
    #5;
    opco=4'b1000;
    #5;
    opco=4'b1001;
    #5;
    opco=4'b1010;
     #5;
    opco=4'b1011;
    #5;
    opco=4'b1100;
    #5;
    opco=4'b1101;
    #5;
    opco=4'b1110;
    #5;
    opco=4'b1111;
    #5;
     $finish();
  end
  initial 
    $monitor("init=%b opco=%b a=%b b=%b deco=%b add=%b sub=%b mul=%b div=%b andd=%b orr=%b nott=%b nandd=%b norr=%b xorr=%b refresh=%b comp=%b sh_result=%b ro_result=%b s=%b ccin=%b cc=%b xs3tens_bit=%b xs5tens_bit=%b bcdtens_bit=%b rfetch=%b out=%b carryflag=%b logflag=%b zeroflag=%b shiftflag=%b doneflag=%b",init,opco,a,b,deco,add,sub,mul,div,andd,orr,nott,nandd,norr,xorr,refresh,comp,sh_result,ro_result,s,ccin,cc,xs3tens_bit,xs5tens_bit,bcdtens_bit,rfetch,out,carryflag,logflag,zeroflag,shiftflag,doneflag);
endmodule

waveform.vcd
$date
	Tue Feb 24 04:13:58 2026
$end

$version
	Synopsys VCS version X-2025.06-SP1_Full64
$end

$timescale
	1ns
$end

$comment Csum: 1 43315df540933998 $end


$scope module tb $end
$var reg 1 ! init $end
$var reg 4 " opco [3:0] $end
$var reg 8 # a [7:0] $end
$var reg 8 $ b [7:0] $end
$var wire 16 % deco [15:0] $end
$var wire 8 & add [7:0] $end
$var wire 8 ' sub [7:0] $end
$var wire 16 ( mul [15:0] $end
$var wire 8 ) div [7:0] $end
$var wire 8 * andd [7:0] $end
$var wire 8 + orr [7:0] $end
$var wire 8 , nott [7:0] $end
$var wire 8 - nandd [7:0] $end
$var wire 8 . norr [7:0] $end
$var wire 8 / xorr [7:0] $end
$var wire 8 0 refresh [7:0] $end
$var wire 8 1 comp [7:0] $end
$var wire 8 2 sh_result [7:0] $end
$var wire 8 3 ro_result [7:0] $end
$var wire 8 4 s [7:0] $end
$var wire 8 5 ccin [7:0] $end
$var wire 4 6 cc [3:0] $end
$var wire 5 7 rfetch [4:0] $end
$var wire 16 8 out [15:0] $end
$var wire 1 9 carryflag $end
$var wire 1 : logflag $end
$var wire 1 ; zeroflag $end
$var wire 1 < shiftflag $end
$var wire 1 = doneflag $end
$var wire 9 > temp_sum [8:0] $end
$var wire 8 ? shl [7:0] $end
$var wire 8 @ shr [7:0] $end
$var wire 8 A shll [7:0] $end
$var wire 8 B shrr [7:0] $end
$var wire 8 C rol [7:0] $end
$var wire 8 D ror [7:0] $end
$var wire 8 E roll [7:0] $end
$var wire 8 F rorr [7:0] $end
$var wire 8 G g [7:0] $end
$var wire 8 H xs3 [7:0] $end
$var wire 8 I xs5 [7:0] $end
$var wire 8 J bcd [7:0] $end
$var wire 1 K xs3tens_bit $end
$var wire 1 L xs5tens_bit $end
$var wire 1 M bcdtens_bit $end
$var wire 1 N arth_flag $end
$var wire 1 O logi_flag $end
$var wire 1 P comp_flag $end
$var wire 1 Q shft_flag $end
$var wire 1 R code_flag $end

$scope module uut $end
$var wire 1 ! init $end
$var wire 4 " opco [3:0] $end
$var wire 8 # a [7:0] $end
$var wire 8 $ b [7:0] $end
$var reg 16 % deco [15:0] $end
$var reg 8 & add [7:0] $end
$var reg 8 ' sub [7:0] $end
$var reg 16 ( mul [15:0] $end
$var reg 8 ) div [7:0] $end
$var reg 8 * andd [7:0] $end
$var reg 8 + orr [7:0] $end
$var reg 8 , nott [7:0] $end
$var reg 8 - nandd [7:0] $end
$var reg 8 . norr [7:0] $end
$var reg 8 / xorr [7:0] $end
$var reg 8 0 refresh [7:0] $end
$var reg 8 1 comp [7:0] $end
$var reg 8 2 sh_result [7:0] $end
$var reg 8 3 ro_result [7:0] $end
$var reg 8 4 s [7:0] $end
$var reg 8 5 ccin [7:0] $end
$var reg 4 6 cc [3:0] $end
$var reg 1 K xs3tens_bit $end
$var reg 1 L xs5tens_bit $end
$var reg 1 M bcdtens_bit $end
$var reg 5 7 rfetch [4:0] $end
$var reg 16 8 out [15:0] $end
$var reg 1 9 carryflag $end
$var reg 1 : logflag $end
$var reg 1 ; zeroflag $end
$var reg 1 < shiftflag $end
$var reg 1 = doneflag $end
$var reg 9 S temp_sum [8:0] $end
$var wire 1 T s1 $end
$var wire 1 U s2 $end
$var reg 8 V shl [7:0] $end
$var reg 8 W shr [7:0] $end
$var reg 8 X shll [7:0] $end
$var reg 8 Y shrr [7:0] $end
$var reg 8 Z rol [7:0] $end
$var reg 8 [ ror [7:0] $end
$var reg 8 \ roll [7:0] $end
$var reg 8 ] rorr [7:0] $end
$var reg 8 ^ g [7:0] $end
$var reg 8 _ xs3 [7:0] $end
$var reg 8 ` xs5 [7:0] $end
$var reg 8 a bcd [7:0] $end
$var reg 1 b arth_flag $end
$var reg 1 c logi_flag $end
$var reg 1 d comp_flag $end
$var reg 1 e shft_flag $end
$var reg 1 f code_flag $end
$upscope $end

$upscope $end

$enddefinitions $end

#0
$dumpvars
0b
0f
0d
0!
0c
xT
xU
0e
0M
09
0=
0:
0<
0K
0L
0;
bxxxxxxxx #
bxxxxxxxx $
b00000000 a
b00000000 ^
bxxxx "
b00000000 Z
b00000000 \
b00000000 [
b00000000 ]
b00000000 V
b00000000 X
b00000000 W
b00000000 Y
bxxxxxxxxx S
b00000000 &
b00000000 *
b0000 6
b00000000 5
b00000000 1
b0000000000000000 %
b00000000 )
b0000000000000000 (
b00000000 -
b00000000 .
b00000000 ,
b00000000 +
b0000000000000000 8
b00000000 0
b00000 7
b00000000 3
b00000000 4
b00000000 2
b00000000 '
b00000000 /
b00000000 _
b00000000 `
zR
zQ
zP
zO
zN
bzzzzzzzz J
bzzzzzzzz I
bzzzzzzzz H
bzzzzzzzz G
bzzzzzzzz F
bzzzzzzzz E
bzzzzzzzz D
bzzzzzzzz C
bzzzzzzzz B
bzzzzzzzz A
bzzzzzzzz @
bzzzzzzzz ?
bzzzzzzzzz >
$end
#5
b11100010 #
b10001100 $
0U
1T
1!
b10001100 5
#10
b0000 "
#15
b0001 "
b0000000000000001 %
19
b01101110 &
b101101110 S
b0000000001101110 8
#20
b0010 "
b0000000000000010 %
09
b01010110 '
b0000000001010110 8
#25
b0011 "
b0000000000000100 %
b0111101110011000 (
b0111101110011000 8
#30
b0100 "
b0000000000001000 %
b00000001 )
b0000000000000001 8
#35
b0101 "
b0000000000010000 %
1:
b10000000 *
b0000000010000000 8
#40
b0110 "
b0000000000100000 %
b11101110 +
b0000000011101110 8
#45
b0111 "
b0000000001000000 %
b00011101 ,
b0000000000011101 8
#50
b1000 "
b0000000010000000 %
b01111111 -
b0000000001111111 8
#55
b1001 "
b0000000100000000 %
b00010001 .
b0000000000010001 8
#60
b1010 "
b0000001000000000 %
b01101110 /
b0000000001101110 8
#65
b1011 "
b0000010000000000 %
0:
b0000000000000000 8
#70
b1100 "
b0000000000000000 %
b0000100000000000 %
b10000000 1
b0000000010000000 8
#75
b1101 "
b0000000000000000 %
b11110111 4
b11110111 3
b11110101 2
b0001000000000000 %
b11100010 \
b01110001 [
b11000101 Z
b01110001 W
1<
b11000100 V
b0000000011110111 8
b11110111 5
#80
b1110 "
b0000000000000000 %
b0101 6
b0010000000000000 %
1=
1M
b00000101 a
b0000000000000101 8
#85
b1111 "
b0000000000000000 %
0=
0M
b11111 7
1f
1e
1d
1c
1b
b0100000000000000 %
b0000000000011111 8
